SHACL2SPARQLpy/DependencyGraphImpl.py
SHACL2SPARQLpy/Eval.py
SHACL2SPARQLpy/RuleBasedValidation.py
SHACL2SPARQLpy/SchemaImpl.py
SHACL2SPARQLpy/Shape.py
SHACL2SPARQLpy/ShapeNetwork.py
SHACL2SPARQLpy/ShapeParser.py
SHACL2SPARQLpy/VariableGenerator.py
SHACL2SPARQLpy/__init__.py
SHACL2SPARQLpy/constraints/Constraint.py
SHACL2SPARQLpy/constraints/MaxOnlyConstraint.py
SHACL2SPARQLpy/constraints/MinMaxConstraint.py
SHACL2SPARQLpy/constraints/MinOnlyConstraint.py
SHACL2SPARQLpy/constraints/__init__.py
SHACL2SPARQLpy/core/Literal.py
SHACL2SPARQLpy/core/Query.py
SHACL2SPARQLpy/core/RuleMap.py
SHACL2SPARQLpy/core/RulePattern.py
SHACL2SPARQLpy/core/__init__.py
SHACL2SPARQLpy/sparql/QueryGenerator.py
SHACL2SPARQLpy/sparql/SPARQLEndpoint.py
SHACL2SPARQLpy/sparql/__init__.py
SHACL2SPARQLpy/utils/RuleBasedValidStats.py
SHACL2SPARQLpy/utils/__init__.py
SHACL2SPARQLpy/utils/fileManagement.py
SHACL2SPARQLpy/utils/globals.py
SHACL2SPARQLpy-1.3.0.dist-info/LICENSE
SHACL2SPARQLpy-1.3.0.dist-info/METADATA
SHACL2SPARQLpy-1.3.0.dist-info/WHEEL
SHACL2SPARQLpy-1.3.0.dist-info/top_level.txt
SHACL2SPARQLpy-1.3.0.dist-info/RECORD
