Metadata-Version: 2.1
Name: SHACL2SPARQLpy
Version: 1.3.0
Summary: Python reference implementation of SHACL2SPARQL
Home-page: https://github.com/SDM-TIB/SHACL2SPARQLpy
Download-URL: https://github.com/SDM-TIB/SHACL2SPARQLpy/archive/refs/tags/v1.3.0.tar.gz
Author: Mónica Figuera, Philipp D. Rohde
Author-email: philipp.rohde@tib.eu
License: MIT
Classifier: Development Status :: 4 - Beta
Classifier: Programming Language :: Python
Classifier: Programming Language :: Python :: 3
Classifier: Programming Language :: Python :: 3 :: Only
Classifier: Programming Language :: Python :: 3.7
Classifier: Programming Language :: Python :: 3.8
Classifier: Programming Language :: Python :: 3.9
Classifier: Programming Language :: Python :: 3.10
Classifier: Programming Language :: Python :: 3.11
Classifier: License :: OSI Approved :: MIT License
Classifier: Operating System :: OS Independent
Classifier: Intended Audience :: Science/Research
Requires-Python: >=3.7
License-File: LICENSE
Requires-Dist: SPARQLWrapper (>=1.8.5)
Requires-Dist: rdflib (>=6.0.0)
